blitzchain/__init__.py
blitzchain/api.py
blitzchain/document_splitter.py
blitzchain/splitter.py
blitzchain/utils.py
cli/__init__.py
cli/main.py
BlitzChain-0.8.2.dist-info/LICENSE
BlitzChain-0.8.2.dist-info/METADATA
BlitzChain-0.8.2.dist-info/WHEEL
BlitzChain-0.8.2.dist-info/top_level.txt
BlitzChain-0.8.2.dist-info/RECORD
