Metadata-Version: 2.1
Name: BlitzChain
Version: 0.8.2
Summary: BlitzChain
Home-page: https://github.com/mr-gpt/blitzchain
Author: Twilix
Author-email: jacky@twilix.io
License-File: LICENSE
Requires-Dist: requests
